zuul_stats_client/__init__.py
zuul_stats_client/__main__.py
zuul_stats_client/main.py
zuul_stats_client/old.py
zuul_stats_client/pipeline.py
zuul_stats_client/tenants.py
zuul_stats_client/utils.py
zuul_stats_client/tests/__init__.py
zuul_stats_client/tests/test_utils.py
zuul_stats_client/tests/samples/sampledata.json
zuul_stats_client-0.0.4.dist-info/AUTHORS
zuul_stats_client-0.0.4.dist-info/LICENSE
zuul_stats_client-0.0.4.dist-info/METADATA
zuul_stats_client-0.0.4.dist-info/WHEEL
zuul_stats_client-0.0.4.dist-info/entry_points.txt
zuul_stats_client-0.0.4.dist-info/pbr.json
zuul_stats_client-0.0.4.dist-info/top_level.txt
zuul_stats_client-0.0.4.dist-info/RECORD
