Metadata-Version: 2.1
Name: zuul-stats-client
Version: 0.0.4
Summary: 'Zuul stats client'
Home-page: http://www.softwarefactory-project.io/
Author: Javier Peña
Author-email: jpena@redhat.com
License: UNKNOWN
Platform: UNKNOWN
Classifier: Development Status :: 3 - Alpha
Classifier: License :: OSI Approved :: Apache Software License
Classifier: Programming Language :: Python
Classifier: Programming Language :: Python :: 2
Classifier: Programming Language :: Python :: 2.7
Classifier: Programming Language :: Python :: 3
Classifier: Programming Language :: Python :: 3.2
Classifier: Intended Audience :: Developers
Classifier: Environment :: Console
Requires-Dist: cliff
Requires-Dist: pbr
Requires-Dist: requests
